{"stats":{"minecraft:custom":{"minecraft:jump":29,"minecraft:time_since_rest":32276,"minecraft:damage_dealt":10,"minecraft:crouch_one_cm":647,"minecraft:play_one_minute":32276,"minecraft:sprint_one_cm":211,"minecraft:interact_with_loom":1,"minecraft:time_since_death":32276,"minecraft:walk_one_cm":15599,"minecraft:interact_with_beacon":4,"minecraft:trigger_trapped_chest":1,"minecraft:sneak_time":606,"minecraft:climb_one_cm":1145,"minecraft:talked_to_villager":1,"minecraft:fly_one_cm":153385,"minecraft:interact_with_brewingstand":1},"minecraft:used":{"relics:runic_altar":1,"enchantinginfuser:enchanting_infuser":1,"minecraft:stone":28,"minecraft:cobblestone":182,"minecraft:villager_spawn_egg":1}},"DataVersion":2586}